setup.py
elasticsearchaws/__init__.py
elasticsearchaws.egg-info/PKG-INFO
elasticsearchaws.egg-info/SOURCES.txt
elasticsearchaws.egg-info/dependency_links.txt
elasticsearchaws.egg-info/not-zip-safe
elasticsearchaws.egg-info/requires.txt
elasticsearchaws.egg-info/top_level.txt