Metadata-Version: 1.0
Name: elasticsearchaws
Version: 1.0
Summary: Elasticsearch connection class for AWS
Home-page: http://github.com/humeniukd/elasticsearch-aws
Author: Dmytro Humeniuk
Author-email: dmitry.gumenyuk@gmail.com
License: MIT
Platform: UNKNOWN
